showtime/__init__.py
showtime/api.py
showtime/command.py
showtime/config.py
showtime/database.py
showtime/output.py
showtime/showtime.py
showtime/types.py
showtime_cli-0.3.20.dist-info/LICENSE
showtime_cli-0.3.20.dist-info/METADATA
showtime_cli-0.3.20.dist-info/WHEEL
showtime_cli-0.3.20.dist-info/entry_points.txt
showtime_cli-0.3.20.dist-info/top_level.txt
showtime_cli-0.3.20.dist-info/RECORD
